pyndustry/__init__.py
pyndustry/processor.py
pyndustry/pyndustry.py
pyndustry/control/__init__.py
pyndustry/control/control.py
pyndustry/game_data/__init__.py
pyndustry/game_data/blocks.py
pyndustry/game_data/items.py
pyndustry/game_data/liquids.py
pyndustry/game_data/units.py
pyndustry/graphics/__init__.py
pyndustry/graphics/graphics.py
pyndustry/graphics/sprites/__init__.py
pyndustry/graphics/sprites/blocks.py
pyndustry/graphics/sprites/items.py
pyndustry/graphics/sprites/liquids.py
pyndustry/graphics/sprites/units.py
pyndustry/memory/__init__.py
pyndustry/memory/memory.py
pyndustry/unit/__init__.py
pyndustry/unit/names.py
pyndustry/unit/types.py
pyndustry-0.1.2.dist-info/METADATA
pyndustry-0.1.2.dist-info/WHEEL
pyndustry-0.1.2.dist-info/top_level.txt
pyndustry-0.1.2.dist-info/RECORD
