Metadata-Version: 2.1
Name: pyndustry
Version: 0.1.2
Summary: description
Home-page: https://github.com/Nawot/pyndustry
Author: Nawot
Author-email: Nawot001@gmail.com
License: UNKNOWN
Project-URL: Bug Tracker, https://github.com/Nawot/pyndustry/issues
Keywords: mindustry
Platform: UNKNOWN
Classifier: Programming Language :: Python :: 3
Requires-Python: >=3.6
Requires-Dist: pyperclip (==1.8.2)
